{
  "number": 35,
  "title": "For the Strength of the Hills",
  "marking": "Energetically",
  "verses": [
    {
      "number": 1,
      "lines": [
        "For the strength of the hills we bless thee,",
        "Our God, our fathers\u2019 God;",
        "Thou hast made thy children mighty",
        "By the touch of the mountain sod.",
        "Thou hast led thy chosen Israel",
        "To freedom\u2019s last abode;",
        "For the strength of the hills we bless thee,",
        "Our God, our fathers\u2019 God."
      ]
    },
    {
      "number": 2,
      "lines": [
        "At the hands of foul oppressors",
        "We\u2019ve borne and suffered long;",
        "Thou hast been our help in weakness,",
        "And thy pow\u2019r hath made us strong.",
        "Amid ruthless foes outnumbered",
        "In weariness we trod;",
        "For the strength of the hills we bless thee,",
        "Our God, our fathers\u2019 God."
      ]
    },
    {
      "number": 3,
      "lines": [
        "Thou hast led us here in safety",
        "Where the mountain bulwark stands",
        "As the guardian of the loved ones",
        "Thou hast brought from many lands.",
        "For the rock and for the river,",
        "The valley\u2019s fertile sod,",
        "For the strength of the hills we bless thee,",
        "Our God, our fathers\u2019 God."
      ]
    },
    {
      "number": 4,
      "lines": [
        "We are watchers of a beacon",
        "Whose light must never die;",
        "We are guardians of an altar",
        "\u2019Midst the silence of the sky.",
        "Here the rocks yield founts of courage,",
        "Struck forth as by thy rod;",
        "For the strength of the hills we bless thee,",
        "Our God, our fathers\u2019 God."
      ]
    }
  ],
  "credits": [
    "Text: Felicia D. Hemans, 1793\u20131835; adapted by Edward L. Sloan, 1830\u20131874",
    "Music: Evan Stephens, 1854\u20131930"
  ],
  "slug": "for-the-strength-of-the-hills",
  "weblink": "https:\/\/www.churchofjesuschrist.org\/study\/manual\/hymns\/for-the-strength-of-the-hills?lang=eng",
  "permalink": "https:\/\/raw.githubusercontent.com\/pendenga\/hymn-lyrics\/hymns-of-the-church-of-jesus-christ-of-latter-day-saints\/eng\/for-the-strength-of-the-hills.json"
}