{
  "number": 7,
  "title": "Id, vosotros mensajeros",
  "marking": "Con reverencia",
  "verses": [
    {
      "number": 1,
      "lines": [
        "Id, vosotros mensajeros",
        "que ten\u00e9is poder de Dios;",
        "publicad el Evangelio",
        "a los pueblos en error."
      ]
    },
    {
      "number": 2,
      "lines": [
        "Id al valle y al monte",
        "el mandato a cumplir;",
        "a los hijos de Jacob",
        "hacedles a Si\u00f3n venir."
      ]
    },
    {
      "number": 3,
      "lines": [
        "Y ver\u00e9is que los conversos",
        "alabanzas os dar\u00e1n,",
        "y premiado por el cielo",
        "el servicio fiel ser\u00e1."
      ]
    },
    {
      "number": 4,
      "lines": [
        "Bellos himnos de gran gozo",
        "los conversos cantar\u00e1n,",
        "y con gloria coronados",
        "por el Rey Jes\u00fas ser\u00e1n."
      ]
    }
  ],
  "credits": [
    "Letra: John Taylor, 1808\u20131887.",
    "M\u00fasica: F. Christensen; arreglo \u00a9 1985 IRI"
  ],
  "slug": "go-ye-messengers-of-heaven",
  "weblink": "https:\/\/www.churchofjesuschrist.org\/study\/manual\/hymns\/go-ye-messengers-of-heaven?lang=spa",
  "permalink": "https:\/\/raw.githubusercontent.com\/pendenga\/hymn-lyrics\/hymns-of-the-church-of-jesus-christ-of-latter-day-saints\/spa\/go-ye-messengers-of-heaven.json"
}