{
  "number": 116,
  "title": "Jes\u00fas, en la corte celestial",
  "marking": "Con serenidad",
  "verses": [
    {
      "number": 1,
      "lines": [
        "Jes\u00fas, en la corte celestial,",
        "mostr\u00f3 Su gran amor",
        "al ofrecerse a venir",
        "y ser el Salvador."
      ]
    },
    {
      "number": 2,
      "lines": [
        "Su vida libremente dio;",
        "Su sangre derram\u00f3.",
        "Su sacrificio de amor",
        "al mundo rescat\u00f3."
      ]
    },
    {
      "number": 3,
      "lines": [
        "Por obediencia a Su Dios,",
        "el premio \u00c9l gan\u00f3.",
        "\u201cOh Dios, Tu voluntad har\u00e9\u201d,",
        "humilde, repiti\u00f3."
      ]
    },
    {
      "number": 4,
      "lines": [
        "Marc\u00f3 la senda y nos gui\u00f3",
        "a esa gran ciudad",
        "do hemos de vivir con Dios",
        "por la eternidad."
      ]
    },
    {
      "number": 5,
      "lines": [
        "Comamos y bebamos, pues,",
        "con mansa humildad,",
        "pues dio Su vida el Se\u00f1or",
        "por la humanidad."
      ],
      "optional": true
    },
    {
      "number": 6,
      "lines": [
        "Oh cu\u00e1n glorioso y cabal",
        "el plan de redenci\u00f3n:",
        "merced, justicia y amor",
        "en celestial uni\u00f3n.",
        "Las estrofas 1, 2, 5 y 6 son especialmente aptos para la Santa Cena."
      ],
      "optional": true
    }
  ],
  "credits": [
    "Letra: Eliza R. Snow, 1804\u20131887.",
    "M\u00fasica: Thomas McIntyre, 1833\u20131914."
  ],
  "slug": "how-great-the-wisdom-and-the-love",
  "weblink": "https:\/\/www.churchofjesuschrist.org\/study\/manual\/hymns\/how-great-the-wisdom-and-the-love?lang=spa",
  "permalink": "https:\/\/raw.githubusercontent.com\/pendenga\/hymn-lyrics\/hymns-of-the-church-of-jesus-christ-of-latter-day-saints\/spa\/how-great-the-wisdom-and-the-love.json"
}