{
  "number": 175,
  "title": "A donde me mandes ir\u00e9",
  "marking": "Con resoluci\u00f3n",
  "verses": [
    {
      "number": 1,
      "lines": [
        "Quiz\u00e1s no tenga yo que cruzar",
        "monta\u00f1as ni ancho mar;",
        "quiz\u00e1s no sea a lucha cruel",
        "que Cristo me quiera enviar.",
        "Mas si \u00c9l me llama a sendas que",
        "yo nunca camin\u00e9,",
        "confiando en \u00c9l, le dir\u00e9: Se\u00f1or,",
        "a donde me mandes, ir\u00e9.",
        "A donde me mandes ir\u00e9, Se\u00f1or,",
        "a monta\u00f1as o islas del mar.",
        "Dir\u00e9 lo que quieras que diga, Se\u00f1or,",
        "y lo que T\u00fa quieras, ser\u00e9."
      ]
    },
    {
      "number": 2,
      "lines": [
        "Habr\u00e1 palabras de fe y paz",
        "que me mande el Se\u00f1or decir;",
        "yo s\u00e9 que en sendas de la maldad",
        "hay seres que redimir.",
        "Se\u00f1or, si Tu quieres mi gu\u00eda ser,",
        "la senda seguir\u00e9;",
        "Tu bello mensaje podr\u00e9 anunciar,",
        "y lo que me mandes dir\u00e9.",
        "A donde me mandes ir\u00e9, Se\u00f1or,",
        "a monta\u00f1as o islas del mar.",
        "Dir\u00e9 lo que quieras que diga, Se\u00f1or,",
        "y lo que T\u00fa quieras, ser\u00e9."
      ]
    },
    {
      "number": 3,
      "lines": [
        "Habr\u00e1 quiz\u00e1s alg\u00fan lugar,",
        "en vi\u00f1as de mi Se\u00f1or,",
        "en donde pueda con fe servir",
        "a Cristo mi Salvador.",
        "Y siempre confiando en Su bondad,",
        "Sus dones recibir\u00e9.",
        "Alegre, har\u00e9 Su voluntad,",
        "y lo que me mande, ser\u00e9.",
        "A donde me mandes ir\u00e9, Se\u00f1or,",
        "a monta\u00f1as o islas del mar.",
        "Dir\u00e9 lo que quieras que diga, Se\u00f1or,",
        "y lo que T\u00fa quieras, ser\u00e9."
      ]
    }
  ],
  "credits": [
    "Letra: Mary Brown, 1856\u20131918.",
    "M\u00fasica: Carrie E. Rounsefell, 1861\u20131930."
  ],
  "slug": "ill-go-where-you-want-me-to-go",
  "weblink": "https:\/\/www.churchofjesuschrist.org\/study\/manual\/hymns\/ill-go-where-you-want-me-to-go?lang=spa",
  "permalink": "https:\/\/raw.githubusercontent.com\/pendenga\/hymn-lyrics\/hymns-of-the-church-of-jesus-christ-of-latter-day-saints\/spa\/ill-go-where-you-want-me-to-go.json"
}